{
    "metaDataVersion": "1.0.0",
    "category": "com.microchip.ide.project",
    "content": {
        "metaDataVersion": "1.1.0",
        "name": "com.microchip.mcu8.mplabx.project.pic18f16q41-uart-hello-world-mplab-mcc",
        "version": "1.0.1",
        "displayName": "Printing Hello World using  UART for PIC18F16Q41",
        "projectName": "pic18f16q41-uart-hello-world-mplab-mcc",
        "shortDescription": "Hello World printed to terminal emulator",
        "ide": {
            "name": "MPLAB X",
            "semverRange": ">=5.40.0"
        },
        "compiler": [
			{
				"name": "XC8",
				"semverRange": "^2.20.0"
			}
		],
        "dfp": {
            "name": "PIC18F-Q_DFP",
            "semverRange": "^1.5.124"
        },
        "configurator": {
            "name": "MCC",
            "semverRange": ">=4.1.0"
        },
        "device": {
            "metaDataVersion": "1.0.0",
            "category": "com.microchip.portal.contentRef",
            "content": {
                "metaDataVersion": "1.0.0",
                "category": "com.microchip.device",
                "name": "",
                "versionRange": "*"
            }
        },
        "author": "Microchip",
        "subcategories": [ "MCC"
        ],
        "peripherals": [ "UART"
        ],
        "keywords": [ "MCC"
        ],
		"additionalData": {
			"longDescription": {
				"metaDataVersion": "1.0.0",
				"category": "com.microchip.portal.fileRef",
				"content": {
					"metaDataVersion": "1.0.0",
					"fileName": "./README.md",
					"mimeType": "text/markdown"
				}
			}
		}
	}
}
